.gitignore
.travis.yml
CHANGES.txt
README.rst
setup.cfg
setup.py
docs/Makefile
docs/api.rst
docs/conf.py
docs/index.rst
docs/install.rst
docs/overview.rst
examples/bench.py
examples/chat.pt
examples/chat.py
examples/shell.py
examples/shellcli.py
pyramid_sockjs/__init__.py
pyramid_sockjs/monkey.py
pyramid_sockjs/paster.py
pyramid_sockjs/protocol.py
pyramid_sockjs/route.py
pyramid_sockjs/session.py
pyramid_sockjs/websocket.py
pyramid_sockjs.egg-info/PKG-INFO
pyramid_sockjs.egg-info/SOURCES.txt
pyramid_sockjs.egg-info/dependency_links.txt
pyramid_sockjs.egg-info/entry_points.txt
pyramid_sockjs.egg-info/not-zip-safe
pyramid_sockjs.egg-info/requires.txt
pyramid_sockjs.egg-info/top_level.txt
pyramid_sockjs/tests/base.py
pyramid_sockjs/tests/test_config.py
pyramid_sockjs/tests/test_protocol.py
pyramid_sockjs/tests/test_route.py
pyramid_sockjs/tests/test_session.py
pyramid_sockjs/tests/test_websocket.py
pyramid_sockjs/transports/__init__.py
pyramid_sockjs/transports/eventsource.py
pyramid_sockjs/transports/htmlfile.py
pyramid_sockjs/transports/jsonp.py
pyramid_sockjs/transports/utils.py
pyramid_sockjs/transports/websocket.py
pyramid_sockjs/transports/xhrpolling.py
pyramid_sockjs/transports/xhrstreaming.py
tests/Makefile
tests/README.md
tests/http-quirks.py
tests/httplib_fork.py
tests/sockjs-protocol-0.3.3.py
tests/sockjs-testsrv.py
tests/utils_03.py