Metadata-Version: 1.1
Name: pyramid-sockjs
Version: 0.3.9
Summary: SockJS server implementation for Pyramid.
Home-page: https://github.com/fafhrd91/pyramid_sockjs/
Author: Nikolay Kim
Author-email: fafhrd91@gmail.com
License: MIT
Platform: UNKNOWN
Classifier: License :: OSI Approved :: MIT License
Classifier: Intended Audience :: Developers
Classifier: Programming Language :: Python
Classifier: Programming Language :: Python :: 2.6
Classifier: Programming Language :: Python :: 2.7
Classifier: Programming Language :: Python :: Implementation :: CPython
Classifier: Framework :: Pyramid
Classifier: Topic :: Internet :: WWW/HTTP
Classifier: Topic :: Internet :: WWW/HTTP :: WSGI
